ltool/__init__.py
ltool/__main__.py
ltool/version.py
ltool/debug/__init__.py
ltool/debug/log_pack.py
ltool/debug/plot.py
ltool/export/__init__.py
ltool/export/export_nc.py
ltool/export/update_scc_db.py
ltool/readers/__init__.py
ltool/readers/get_files.py
ltool/readers/parse_config.py
ltool/readers/read_config.py
ltool/readers/read_scc_db.py
ltool/tools/__init__.py
ltool/tools/geom_dtf.py
ltool/tools/wavelet.py
ltool-1.7.8.dist-info/METADATA
ltool-1.7.8.dist-info/WHEEL
ltool-1.7.8.dist-info/entry_points.txt
ltool-1.7.8.dist-info/top_level.txt
ltool-1.7.8.dist-info/RECORD
