Metadata-Version: 2.1
Name: ltool
Version: 1.7.8
Summary: Automated aerosol layer detection algorithm.
Home-page: http://pypi.python.org/pypi/ltool_v1.7.8/
Author: Nikos Siomos
Author-email: nsiomos@noa.gr
License: UNKNOWN
Platform: UNKNOWN
Classifier: Programming Language :: Python :: 3
Classifier: Operating System :: OS Independent
Requires-Python: >=3.7
Requires-Dist: numpy
Requires-Dist: datetime
Requires-Dist: pandas
Requires-Dist: xarray
Requires-Dist: netCDF4
